CHANGELOG.md
LICENSE
MANIFEST.in
README.md
setup.cfg
setup.py
osmosis_on_premise_driver/__init__.py
osmosis_on_premise_driver/computing_plugin.py
osmosis_on_premise_driver/data_plugin.py
osmosis_on_premise_driver/log.py
osmosis_on_premise_driver_plus.egg-info/PKG-INFO
osmosis_on_premise_driver_plus.egg-info/SOURCES.txt
osmosis_on_premise_driver_plus.egg-info/dependency_links.txt
osmosis_on_premise_driver_plus.egg-info/not-zip-safe
osmosis_on_premise_driver_plus.egg-info/requires.txt
osmosis_on_premise_driver_plus.egg-info/top_level.txt
tests/__init__.py
tests/test_computing_plugin.py
tests/test_data_plugin.py