Metadata-Version: 2.1
Name: osmosis-on-premise-driver-plus
Version: 0.0.6
Summary: 💧 Osmosis On Premise Driver Implementation
Home-page: https://github.com/marcojrfurtado/osmosis-on-premise-driver-plus
Author: marcojrfurtado
Author-email: devops@oceanprotocol.com
License: Apache Software License 2.0
Keywords: osmosis-on-premise-driver-plus
Platform: UNKNOWN
Classifier: Development Status :: 2 - Pre-Alpha
Classifier: Intended Audience :: Developers
Classifier: License :: OSI Approved :: Apache Software License
Classifier: Natural Language :: English
Classifier: Programming Language :: Python :: 3.6
Classifier: Programming Language :: Python :: 3.7
Provides-Extra: dev
Provides-Extra: docs
Provides-Extra: test
